MANIFEST.in
VERSION
setup.py
docs/source/conf.py
examples/oauth2-callback.py
examples/picqer-list-products.py
examples/picqer-list-webhooks.py
examples/picqer-ratelimit.py
examples/picqer-traverse-api.py
examples/piqcer-list-picklist-products.py
examples/shopify-get-orders.py
examples/shopify-inspect-catalog.py
examples/shopify-ratelimit.py
examples/shopify-set-inventory.py
headless/package.json
headless.egg-info/PKG-INFO
headless.egg-info/SOURCES.txt
headless.egg-info/dependency_links.txt
headless.egg-info/requires.txt
headless.egg-info/top_level.txt
headless/core/__init__.py
headless/core/deferredresource.py
headless/core/linearbackoff.py
headless/core/resource.py
headless/core/resourcemeta.py
headless/core/resourcemetaclass.py
headless/core/resourcereference.py
headless/core/httpx/__init__.py
headless/core/httpx/client.py
headless/core/httpx/request.py
headless/core/httpx/response.py
headless/ext/oauth2/__init__.py
headless/ext/oauth2/client.py
headless/ext/oauth2/clientcredential.py
headless/ext/oauth2/const.py
headless/ext/oauth2/nullcredential.py
headless/ext/oauth2/server.py
headless/ext/oauth2/models/__init__.py
headless/ext/oauth2/models/authorizationcode.py
headless/ext/oauth2/models/authorizationendpointresponse.py
headless/ext/oauth2/models/authorizationrequest.py
headless/ext/oauth2/models/bearertokencredential.py
headless/ext/oauth2/models/claimset.py
headless/ext/oauth2/models/clientauthenticationmethod.py
headless/ext/oauth2/models/clientcredentialsrequest.py
headless/ext/oauth2/models/error.py
headless/ext/oauth2/models/iobtainable.py
headless/ext/oauth2/models/jsonwebtoken.py
headless/ext/oauth2/models/oidctoken.py
headless/ext/oauth2/models/servermetadata.py
headless/ext/oauth2/models/subjectidentifier.py
headless/ext/oauth2/models/tokenresponse.py
headless/ext/oauth2/test/discovery.py
headless/ext/oauth2/test/manual.py
headless/ext/oauth2/types/__init__.py
headless/ext/oauth2/types/granttype.py
headless/ext/oauth2/types/responsemode.py
headless/ext/oauth2/types/responsetype.py
headless/ext/picqer/__init__.py
headless/ext/picqer/client.py
headless/ext/picqer/credential.py
